stfd/__init__.py
stfd/_compat.py
stfd/_metadata.py
stfd/_version.py
stfd/data/__init__.py
stfd/model/__init__.py
stfd/model/_model_builder.py
stfd/model/_model_utils.py
stfd/model/_primitives.py
stfd/model/_spatial_gene_sets.py
stfd/model/_spatial_ldm.py
stfd/model/_spatial_model.py
stfd/model/_spatial_modeling_utils.py
stfd/plotting/__init__.py
stfd/plotting/_palettes.py
stfd/plotting/_spatial_plot.py
stfd/tool/__init__.py
stfd/utils/__init__.py
stfd/utils/_compat.py
stfd/utils/_decorators.py
stfd/utils/_logger.py
stfd/utils/_utilities.py
STFD-0.0.1.dist-info/METADATA
STFD-0.0.1.dist-info/WHEEL
STFD-0.0.1.dist-info/dependency_links.txt
STFD-0.0.1.dist-info/top_level.txt
STFD-0.0.1.dist-info/RECORD
