Metadata-Version: 2.1
Name: STFD
Version: 0.0.1
Summary: STFD: Series of deep learning-based foundation models for spatial transcriptomic data analysis
Home-page: https://github.com/
Author: Ziwei Xue
Author-email: ziwei.21@intl.zju.edu.cn
License: UNKNOWN
Platform: UNKNOWN
Requires-Python: >=3.9
Requires-Dist: scatlasvae
Requires-Dist: labw-utils ==1.0.3
Requires-Dist: numba ==0.57.1
Requires-Dist: numpy ==1.21.6
Requires-Dist: pandas ==1.4.2
Requires-Dist: omegaconf ==2.3.0
Requires-Dist: pytorch-lightning ==2.2.0.post0
Requires-Dist: scikit-image ==0.20.0
Requires-Dist: opencv-python ==4.9.0
Requires-Dist: transformers ==4.17.0
Requires-Dist: datasets ==2.1.0
Requires-Dist: anndata ==0.8.0
Requires-Dist: scanpy ==1.8.1
Requires-Dist: scikit-learn ==0.24.1
Requires-Dist: matplotlib ==3.3.4
Requires-Dist: einops ==0.4.1
Requires-Dist: biopython ==1.79
Requires-Dist: seaborn ==0.12.2
Requires-Dist: sinfonia ==0.0.3
Requires-Dist: tabulate ==0.9.0
Requires-Dist: logomaker
Requires-Dist: ema-pytorch
Requires-Dist: pytorch-fid
Requires-Dist: accelerate
Provides-Extra: cpu
Requires-Dist: faiss-cpu ==1.7.2 ; extra == 'cpu'
Requires-Dist: torch ==1.13.1 ; extra == 'cpu'
Requires-Dist: torchvision ==0.14.1 ; extra == 'cpu'
Requires-Dist: torchaudio ==0.13.1 ; extra == 'cpu'
Provides-Extra: docs
Requires-Dist: sphinx ==3.2.1 ; extra == 'docs'
Requires-Dist: nbsphinx ==0.8.7 ; extra == 'docs'
Requires-Dist: sphinx-rtd-theme ==1.2.0 ; extra == 'docs'
Requires-Dist: sphinx-hoverxref ==1.3.0 ; extra == 'docs'
Provides-Extra: gpu
Requires-Dist: faiss-gpu ==1.7.2 ; extra == 'gpu'
Requires-Dist: torch ==1.13.1+cu117 ; extra == 'gpu'
Requires-Dist: torchvision ==0.14.1+cu117 ; extra == 'gpu'
Requires-Dist: torchaudio ==0.13.1+cu117 ; extra == 'gpu'
